lab/__init__.py
lab/dataset.py
lab/dirs.py
lab/experiment.py
lab/job.py
lab/lab_facade.py
lab/labresource.py
lab/model.py
lab/storage.py
lab/task.py
lab/task_template.py
transformerlab-0.0.67.dist-info/licenses/LICENSE
transformerlab-0.0.67.dist-info/METADATA
transformerlab-0.0.67.dist-info/WHEEL
transformerlab-0.0.67.dist-info/top_level.txt
transformerlab-0.0.67.dist-info/RECORD
