Metadata-Version: 2.4
Name: transformerlab
Version: 0.0.67
Summary: Python SDK for Transformer Lab
Author-email: Transformer Lab <developers@lab.cloud>
License:                     GNU AFFERO GENERAL PUBLIC LICENSE
Project-URL: Homepage, https://github.com/transformerlab/transformerlab-app
Project-URL: Bug Tracker, https://github.com/transformerlab/transformerlab-app/issues
Requires-Python: >=3.10
License-File: LICENSE
Requires-Dist: werkzeug
Requires-Dist: pytest
Requires-Dist: pytest-asyncio
Requires-Dist: wandb
Requires-Dist: fsspec
Requires-Dist: s3fs
Requires-Dist: aiofiles
Requires-Dist: gcsfs
Dynamic: license-file
